dev_utils/__init__.py
dev_utils/google_apis/google_sheet/gsheet_wrapper.py
dev_utils/lark_wrapper/__init__.py
dev_utils/lark_wrapper/const.py
dev_utils/lark_wrapper/messege_lark.py
dev_utils/lark_wrapper/model.py
dev_utils/lark_wrapper/msg_bot.py
dev_utils/lark_wrapper/sheet_utils.py
dev_utils/logging_utils/__init__.py
dev_utils/logging_utils/logging_utils.py
dev_utils/logging_utils/rotateHandler.py
dev_utils_jokerssd-0.5.2.dist-info/METADATA
dev_utils_jokerssd-0.5.2.dist-info/WHEEL
dev_utils_jokerssd-0.5.2.dist-info/RECORD
