Metadata-Version: 2.4
Name: dev-utils-jokerssd
Version: 0.5.2
Summary: Development utilities with structured logging
Author-email: Jokerssd <jokerssd@example.com>
License: MIT
Classifier: License :: OSI Approved :: MIT License
Classifier: Operating System :: OS Independent
Classifier: Programming Language :: Python :: 3
Requires-Python: >=3.12
Requires-Dist: aiohttp
Requires-Dist: pydantic-gsheets>=0.0.8
Requires-Dist: pydantic[email]>=2.11.10
Requires-Dist: requests
Requires-Dist: structlog>=25.5.0
